mypkg6668/__init__.py
mypkg6668/autoweave.cp38-win_amd64.pyd
mypkg6668-0.1.4.dist-info/METADATA
mypkg6668-0.1.4.dist-info/WHEEL
mypkg6668-0.1.4.dist-info/top_level.txt
mypkg6668-0.1.4.dist-info/RECORD
