Metadata-Version: 2.1
Name: mypkg6668
Version: 0.1.4
Summary: AutoWeave - Import Hook 拦截器
Author-email: AutoWeave <autoweave@example.com>
License: MIT
Keywords: import-hook,interceptor,nuitka,autoweave
Classifier: Development Status :: 3 - Alpha
Classifier: Intended Audience :: Developers
Classifier: License :: OSI Approved :: MIT License
Classifier: Programming Language :: Python :: 3.8
Classifier: Operating System :: OS Independent
Classifier: Topic :: Software Development :: Libraries :: Python Modules
Requires-Python: >=3.8
